LICENSE
MANIFEST.in
README.md
requirements.txt
setup.py
btgsolutions_otcmarkets/__init__.py
btgsolutions_otcmarkets/config.py
btgsolutions_otcmarkets/rest/__init__.py
btgsolutions_otcmarkets/rest/authenticator.py
btgsolutions_otcmarkets/rest/historical_data.py
btgsolutions_otcmarkets/rest/pricing.py
btgsolutions_otcmarkets/rest/reference_data.py
btgsolutions_otcmarkets/rest/risk_status.py
btgsolutions_otcmarkets/rest/top_of_book.py
btgsolutions_otcmarkets/websocket/__init__.py
btgsolutions_otcmarkets/websocket/market_data.py
btgsolutions_otcmarkets/websocket/order_entry.py
btgsolutions_otcmarkets/websocket/websocket_default_functions.py
btgsolutions_otcmarkets_python_client.egg-info/PKG-INFO
btgsolutions_otcmarkets_python_client.egg-info/SOURCES.txt
btgsolutions_otcmarkets_python_client.egg-info/dependency_links.txt
btgsolutions_otcmarkets_python_client.egg-info/requires.txt
btgsolutions_otcmarkets_python_client.egg-info/top_level.txt