Metadata-Version: 2.4
Name: btgsolutions-otcmarkets-python-client
Version: 0.1.0
Summary: Python library to access BTG OTC Markets APIs.
Home-page: https://github.com/BTG-Pactual-Solutions/btgsolutions-otcmarkets-python-client
Author: BTG Solutions
Requires-Python: >=3.7.1
License-File: LICENSE
Requires-Dist: PyJWT>=2.4.0
Requires-Dist: requests>=2.26.0
Requires-Dist: websocket-client>=1.4.1
Requires-Dist: pandas>=1.3.5
Dynamic: author
Dynamic: description
Dynamic: description-content-type
Dynamic: home-page
Dynamic: license-file
Dynamic: requires-dist
Dynamic: requires-python
Dynamic: summary
